{
  "BurtonBrink": "Arcadia, CA",
  "batfefm": "non-location",
  "Katricee71": "Honolulu County, HI",
  "bailey4casenate": "Placerville, CA",
  "guns_win": "non-location",
  "FedUpCitizenLA": "non-location",
  "ElizabethForNV": "Las Vegas, NV",
  "2ANow": "non-location",
  "huang4congress": "Irvine, CA",
  "RedNationRising": "United States",
  "Official_DC": "non-location",
  "Alwaysaloha2021": "United States",
  "FPCAction": "United States",
  "LNakanelua": "Kailua, HI",
  "CallVoter": "United States",
  "akamaimom": "United States",
  "CHIZMAGA": "San Diego, CA",
  "rcurtis808": "United States",
  "Joe_Akana": "United States",
  "A1Firearmsupply": "Bucks County, PA",
  "Joe7993": "United States",
  "lalaviealoha": "United States",
  "LACountyADDA": "Los Angeles, CA",
  "BuzzPatterson": "United States",
  "nettermike": "United States",
  "JoshuaHosler": "Colorado Springs, CO",
  "takecaback": "United States",
  "BattlebornPats": "United States",
  "BourbonDaily": "Louisville, KY",
  "namemeifucan": "United States",
  "aeonexplorer": "non-location",
  "SacDailyPress": "Sacramento, CA",
  "Steveadams76": "Panamá",
  "impeachdummy46": "non-location",
  "Friends4LVK9": "Las Vegas, NV",
  "BishForCongress": "Sacramento County, CA",
  "bowhunter0812": "non-location",
  "ClarkCountyNV": "Las Vegas, NV",
  "bluelivesmtr": "United States",
  "recallgavin2020": "United States",
  "SFValleyGuns": "Los Angeles County, CA",
  "pistis71414528": "United States",
  "DavidFennell": "Chico, CA",
  "RED_ELEPHANT61": "United States",
  "michaelramos": "San Bernardino County, CA",
  "SPORTalkLAKings": "Los Angeles, CA",
  "gold_political": "United States",
  "LAKingsCrowned": "United States",
  "KathyTavoularis": "San Jose, CA",
  "CRPAnews": "Fullerton, CA",
  "GunLover_": "non-location",
  "TheCalRight": "United States",
  "DrewDoughtyljk": "non-location",
  "Cartel_Cal": "United States",
  "CorrinRankin": "United States",
  "TrumpWave1": "United States",
  "charliekirk11": "Phoenix, AZ",
  "RealMattCouch": "United States",
  "CCRPNV": "Las Vegas, NV",
  "BeastJohnCox": "San Diego, CA",
  "HIRANews808": "Ewa Beach, HI",
  "BPDCaptEspinoza": "Barstow, CA",
  "K9Hawaii": "Hawaii County, HI",
  "RVPilar_": "San Diego, CA",
  "Gunalizer": "United States",
  "Duty_Is_Ours": "Ewa Beach, HI",
  "dogeinhawaii": "Honolulu County, HI",
  "Calgunsdotnet": "United States",
  "CRPAPresident": "United States",
  "feelthemana": "non-location",
  "PatriotPartyNV": "non-location",
  "NRCGOPClub": "Las Vegas, NV",
  "AusStuff": "Australia",
  "Prop13Committee": "non-location",
  "808ST8oMind": "United States",
  "ColumbiaBugle": "Washington, DC",
  "nattyb_16": "non-location",
  "myles_b88": "non-location",
  "KATYSaccitizen": "Sacramento, CA",
  "haccident12": "Registro, Brasil",
  "EmpoweringUSA": "non-location",
  "Meljanx": "United States",
  "cgfgunrights": "United States",
  "joegooding": "Irving, TX",
  "kenivan": "non-location",
  "AugieLens": "Los Angeles, CA",
  "bourbonblog": "non-location",
  "MCGOP_CA": "Monterey County, CA",
  "DarylEvans15": "Los Angeles, CA",
  "UT_MtnLion": "South Salt Lake, UT",
  "_Gun_Lover": "non-location",
  "CaliRedGal": "San Francisco, CA",
  "AllenVolunteers": "United States",
  "RobManess": "United States",
  "CaliforniaGlobe": "Sacramento, CA",
  "IWashington": "non-location",
  "robertrarce": "Phoenix, AZ",
  "HawaiiFreePress": "United States",
  "ammarkammo": "non-location",
  "aprilmbean": "Sacramento, CA",
  "tamarabarto": "non-location",
  "billfishgroup": "United States",
  "hihousegop": "Honolulu, HI",
  "toddeherman": "non-location",
  "FarnsFirearms": "Orem, UT",
  "RealErinCruz": "Palm Springs, CA",
  "aloharose808": "United States",
  "WMCNRA": "Los Angeles County, CA",
  "sheribaby81": "Honolulu, HI",
  "Hooyah61": "Tampa, FL",
  "1_LAKINGSFAN": "Pattaya City, Thailand",
  "2aPhilosophy": "non-location",
  "LASDBrink": "Los Angeles, CA",
  "UNLVRebelGrl": "non-location",
  "MarkMeuser": "United States",
  "SenRichardBlack": "United States",
  "walking_inj": "Honolulu County, HI",
  "CAPACTIVATORSUS": "United States",
  "LeftIsntChange": "United States",
  "billpostmus": "non-location",
  "Sassafrass_84": "United States",
  "USMilInsiders": "United States",
  "MauiFreedomTV": "Maui County, HI",
  "MarcelAndRogie": "United States",
  "Dan_in_HI": "Honolulu, HI",
  "ruggedrosaries": "Houston, TX",
  "_Berserker45": "United States",
  "DavidRHamman": "United States",
  "MAGAaTom": "St. Pete Beach, FL",
  "Maximus_ForEVR": "non-location",
  "TaxpayersPlacer": "non-location",
  "jjauthor": "United States",
  "DeanHeller": "Carson City, NV",
  "Amer1stHunter": "non-location",
  "John_John_Qwert": "non-location"
}