{
  "bkbart80": "United States",
  "SaltyMommaC": "Yakima County, WA",
  "FreshSardonic": "non-location",
  "Sassafrass_84": "United States",
  "Scrappy94546226": "Maryville, TN",
  "IntrepidAmerica": "non-location",
  "seancpdx": "non-location",
  "TheWacoKid8": "United States",
  "RobV59": "United States",
  "WUp2022": "non-location",
  "hula_rev": "United States",
  "MeBoomBoomDown": "non-location",
  "terradise74": "United States",
  "ShayzaShay": "United States",
  "XtheDrama": "United States",
  "HistorianUSA1": "Buffalo, NY",
  "ChrisLilBooksto": "United States",
  "0xagonally": "non-location",
  "syl_sylv7966337": "non-location",
  "NoogaJack": "United States",
  "nickberoxbe1989": "United States",
  "vedigu72": "non-location",
  "justicecometh": "United States",
  "Sledgehamm22619": "Canada",
  "1Nicdar": "non-location",
  "CFWBers": "United States",
  "CilComLFC": "non-location",
  "Hawkesbay69": "non-location",
  "crazycorpsman22": "United States",
  "Ghostofcynthia": "non-location",
  "CindyontheBay": "Earth, TX",
  "greyman7107": "non-location",
  "mitchell_l46629": "United States",
  "TheTimDeFelice": "Dukes County, MA",
  "harmless_human": "Cariboo, Canada",
  "Myredrudy1": "Portland, OR",
  "ChrisNoblett": "Bartlett, TN",
  "Michaela_1776": "United States",
  "elephant_23": "United States",
  "OGBoomer3": "Centennial, CO",
  "RT93609537": "non-location",
  "Patriot9791": "United States",
  "Ginagina822": "United States",
  "TammyG5683": "United States",
  "Purrcie": "Lokpha, नेपाल",
  "Mowwow111": "Oregon City, OR",
  "Mr___B9939": "Earth, TX",
  "krfishy1": "non-location",
  "Stillnthewoods": "United States",
  "miriela_prieto": "non-location",
  "strong_side_24": "United States",
  "JohnC32116200": "City of Olean, NY",
  "theewarrant": "non-location",
  "Spike19621": "Roswell, NM",
  "DanielleMejiaCA": "United States",
  "RapidRaccoon": "non-location",
  "coffeeontherox": "United States",
  "Gitmo99": "non-location",
  "WinterBlues1104": "non-location",
  "americancatass": "United States",
  "oregon76mama": "United States",
  "fake_keysersoze": "non-location",
  "Bee522441517990": "Washington, DC",
  "OrSoCoKat": "United States",
  "Prepperradio": "United States",
  "PunditParanoia": "non-location",
  "Nutmeg20201": "United States",
  "JT4DT24": "United States",
  "LetsFindOut16": "non-location",
  "DogRescue1964": "New York, NY",
  "hotnostril": "non-location",
  "OldNevadaElJefe": "Israel",
  "RyderzStorm": "Portland, OR",
  "ebonheizef": "non-location",
  "realBurningBrig": "non-location",
  "TheThe1776": "Sumas, WA",
  "Tiffany34006057": "United States",
  "4thTurning101": "non-location",
  "FirstSpeaker59": "United States",
  "WaGov_US": "non-location",
  "MatthewOBrienSr": "Miami, FL",
  "JustAmyMcC": "United States",
  "JoelBNole": "Jacksonville, FL",
  "ttstrac": "United States",
  "1MrE261816": "non-location",
  "mikcinwashere": "United States",
  "SwampLifeCowgrl": "United States",
  "SDSLLC_USA": "non-location",
  "MahnahmanonII": "Reggio Emilia, Italia",
  "Flier77": "non-location",
  "MorgansAmerica": "United States",
  "JudyHeinken": "United States",
  "HiddenAgendaX": "United States",
  "UberAdele": "Toronto, Canada",
  "2lightenitup": "non-location",
  "RelentlessLaman": "Seattle, WA",
  "brutalamericans": "non-location",
  "drk_2_lite": "United States",
  "Michael30210368": "United States",
  "Johnnieo88": "New York, NY",
  "curt_gallia": "non-location",
  "JohnnyDPhinFan": "non-location",
  "ClownWorldWide": "non-location",
  "FishtoolHand": "United States",
  "extra_thousand": "non-location",
  "silverchickn": "non-location",
  "FoggyMission": "non-location",
  "Da2000Pic": "United States",
  "4D5x5": "non-location",
  "IowaStandard": "United States",
  "fubarspam": "non-location",
  "AntisocialMoth2": "non-location",
  "GovernorDuyck": "Forest Grove, OR",
  "ETOPSFlyerPDX": "Hillsboro, OR",
  "SEMFILTRO21": "non-location",
  "Granite_Stater1": "non-location",
  "stephlrgrs": "Atlanta, GA",
  "BeebeForOregon": "United States",
  "ericschurchnst8": "United States",
  "TheSaraTalks": "United States",
  "_anooshehnouri_": "Livingston County, MI",
  "realHolyLamb": "United States",
  "Coloradokarma__": "United States",
  "politiwars": "United States",
  "wrldnwstoday": "United States",
  "RedPillRedcoat": "non-location",
  "JayT_DuFresne": "United States",
  "Nine41Mc": "non-location",
  "peabodyfmdev": "Portland, OR",
  "astronomy89": "non-location",
  "OneBadDude_": "non-location",
  "StormVet106": "United States",
  "Ak47Mouth": "United States",
  "NudgeNudge77": "United States",
  "pillock66": "non-location",
  "TheEXECUTlONER_": "United States",
  "SteveTheRacoon7": "United States",
  "StevenJBurns": "Abilene, TX",
  "Maga4liberty": "United States",
  "CCDHWatch": "non-location",
  "UngovernableJ81": "non-location",
  "NatalieDunlevey": "non-location",
  "ViolaLeighBlues": "non-location",
  "ClarencDarrow": "non-location",
  "SmallGov4All": "United States",
  "hunnybadgermom": "United States",
  "wendyp4545": "Mount Airy, NC",
  "HerdImmunity12": "United Kingdom",
  "ipaideight": "Kivalliq Region, Canada",
  "ItsYaBoiWoodsy": "United States",
  "sc_exposer": "United States",
  "reg1776": "Owasso, OK",
  "FistPunchX": "Chunky, MS",
  "mandala_mandy": "United States",
  "Random_Walk_PDX": "United States",
  "SECisevil23": "New Orleans, LA",
  "narcotech": "United States",
  "aymee337": "non-location",
  "Apathy_Overdose": "non-location",
  "SquishJD": "United States",
  "NativeTexan_17": "non-location",
  "AFkokogems": "Washington, DC",
  "madlovepatriot": "United States",
  "BaconBullets2": "non-location",
  "apexprepping": "United States",
  "CochiAtl": "Atlanta, GA",
  "esposito1142425": "non-location",
  "KristophenK": "non-location",
  "burgessfour": "United States",
  "h2omaven1": "non-location",
  "WLofMV": "Portland, OR",
  "MattForVA": "Fredericksburg, VA",
  "TheMatrixStorm": "non-location",
  "c_essene": "non-location",
  "Ivajbrowning64": "non-location",
  "ThatBasedDude": "Norwich, United Kingdom",
  "Rural_Mind": "United States",
  "TheFrenchiePug": "United States",
  "Time2_Choose": "non-location",
  "bogie_usa": "United States",
  "therealwildcur": "non-location",
  "Nuked4Every1": "non-location",
  "GodIsAmazing84": "United States",
  "ShannonV1973": "United States",
  "dogmomjenn": "United States",
  "PeriklesGREAT": "non-location",
  "bamajayt": "United States",
  "Consp4Beginners": "non-location",
  "WildOwl25": "non-location",
  "ENDVBM": "United States",
  "nogoodrx": "non-location",
  "KJoD63": "non-location",
  "Tom4theright": "United States",
  "Rusts09": "non-location",
  "T_Q_Gardner": "United States",
  "CryptoBear70": "United States",
  "SpeakTruthDBS": "Knoxville, TN",
  "Crossbearer1956": "United States",
  "McAnecha": "non-location",
  "oscar_z_grouch": "non-location",
  "leti19285": "United States",
  "oregoncitizen_": "United States",
  "rebelyell311": "non-location",
  "oregonducksmama": "United States",
  "lucylocket1700": "Devon, United Kingdom",
  "AngryPayer": "non-location",
  "grey4626": "McKeesport, PA",
  "AnnQueefa1": "non-location",
  "PeaceMakerALDO": "non-location",
  "Michael72172097": "Köln, Deutschland",
  "king_myrna67490": "United States",
  "ManTracker73": "non-location",
  "TinyDancer_1_": "United States",
  "DemoncratsREviI": "United States",
  "GerardKapraun": "United States",
  "PennyDread88": "non-location",
  "Elil2002": "non-location",
  "deltasense1": "Vancouver, Canada",
  "hardwurkindaddy": "non-location",
  "rblank97705": "United States",
  "rbryson711": "non-location",
  "CJAXLING": "United States",
  "Joe7993": "United States",
  "AnthonyG0528": "United States",
  "BoobooWonderdog": "non-location",
  "ClintRegert": "Virginia Beach, VA",
  "RHP2461": "non-location",
  "99788Bud": "non-location",
  "CherieBeneteau": "non-location",
  "Paulmcanally4": "United States",
  "bryan_wade29520": "Houston, TX",
  "pnwliqsun": "non-location",
  "Mr_Pendulum_": "non-location",
  "realZOLA1611": "non-location",
  "LRagoczy": "non-location"
}