{
  "downi75": "United States",
  "luisbaram": "Antarctica",
  "TonyLaneNV": "Las Vegas, NV",
  "CynicalPublius": "non-location",
  "ChristineB56955": "Langhorne Manor, PA",
  "Squill_Mama": "United States",
  "latimeralder": "United Kingdom",
  "WEschenbach": "Napa County, CA",
  "LibBrainRot": "United States",
  "JaniceW78256134": "non-location",
  "ClimateThere": "Cambridgeshire, United Kingdom",
  "njcoast_protect": "United States",
  "timacheson": "non-location",
  "Badged_Patriot": "United States",
  "Milajoy": "Winston-Salem, NC",
  "Climate_Earth20": "West Midlands, United Kingdom",
  "akafaceUS": "United States",
  "robbystarbuck": "Nashville, TN",
  "EricAbbenante": "United States",
  "ImtiazMadmood": "United Kingdom",
  "WallStreetApes": "United States",
  "DaveAtherton20": "Greater London, United Kingdom",
  "DawnTJ90": "Canada",
  "ScottPresler": "non-location",
  "udreams30": "United States",
  "Alladdin1983": "non-location",
  "Iammurphycolet": "Brighton and Hove, United Kingdom",
  "cyclonepride1": "non-location",
  "profstonge": "non-location"
}