{
  "Quickdraw_69": "United States",
  "SuspendedAnd1": "Simcoe, Canada",
  "tarafaul503": "Portland, OR",
  "HoneyBeeSage": "non-location",
  "PapaBearMyers": "United States",
  "marty_twit": "non-location",
  "rightwinghitjob": "Sioux Falls, SD",
  "Brett1Alexander": "Lethbridge, Canada",
  "SystemicTexism": "United States",
  "GodlyPhilosophy": "non-location",
  "The_KanyeTwitty": "United States",
  "Michael72172097": "Köln, Deutschland",
  "szeachmoment": "non-location",
  "kemoshabby": "Austin, TX",
  "RetroCoast": "non-location",
  "MagaMysticLady": "non-location",
  "SHammerson1776": "non-location",
  "CountMntCristo": "United States",
  "oregonducksmama": "United States",
  "FreshSardonic": "non-location",
  "VirgisViews": "United States",
  "davidwall96": "Scottsdale, AZ"
}